image_fragment/__init__.py
image_fragment/fragment.py
image_fragment-0.2.3.dist-info/LICENSE
image_fragment-0.2.3.dist-info/METADATA
image_fragment-0.2.3.dist-info/WHEEL
image_fragment-0.2.3.dist-info/top_level.txt
image_fragment-0.2.3.dist-info/RECORD
