Metadata-Version: 2.1
Name: image-fragment
Version: 0.2.3
Summary: Data Section
Home-page: https://github.com/fuzailpalnak/fragment
Author: Fuzail Palnak
Author-email: fuzailpalnak@gmail.com
Keywords: numpy, Window, Section, Array, Stitch, Split
Classifier: Programming Language :: Python :: 3
Classifier: License :: OSI Approved :: MIT License
Classifier: Operating System :: OS Independent
Requires-Python: ~=3.6
License-File: LICENSE
Requires-Dist: numpy (>=1.19.1)
